tiky.py
tik_data/__init__.py
tik_data/color/__init__.py
tik_data/license/__init__.py
tiky-1.0.6.dist-info/METADATA
tiky-1.0.6.dist-info/WHEEL
tiky-1.0.6.dist-info/entry_points.txt
tiky-1.0.6.dist-info/top_level.txt
tiky-1.0.6.dist-info/RECORD
