Metadata-Version: 2.1
Name: tiky
Version: 1.0.6
Summary: TikTok AutoClaimer.
Home-page: https://tiktokapi.xyz/
Author: Dexy
Author-email: dexy@flamelo.com
License: Dexy License
Keywords: tiktok,autoclaimer,turbo,dexy,api,
Platform: UNKNOWN
Requires-Dist: requests
Requires-Dist: colorama
Requires-Dist: halo
